bidsapps/__init__.py
bidsapps/app_import.py
bidsapps/app_management.py
bidsapps/cli.py
bidsapps/interactive_edit.py
bidsapps/manifest_management.py
bidsapps/query_configs.py
bidsapps/repo_management.py
bidsapps-0.1.0a0.dist-info/METADATA
bidsapps-0.1.0a0.dist-info/WHEEL
bidsapps-0.1.0a0.dist-info/entry_points.txt
bidsapps-0.1.0a0.dist-info/RECORD
