Metadata-Version: 2.3
Name: bidsapps
Version: 0.1.0a0
Summary: CLI tool for running BIDS apps
Requires-Python: <4.0,>=3.8
Requires-Dist: appdirs>=1.4.4
Requires-Dist: click>=8.1.7
Requires-Dist: pulp<2.8.0
Requires-Dist: pyyaml>=6.0.2
Requires-Dist: questionary>=2.0.1
Requires-Dist: requests>=2.32.3
Requires-Dist: rich>=13.9.4
Requires-Dist: snakebids>=0.13.1
